evolvishub_data_handler/__init__.py
evolvishub_data_handler/cdc_handler.py
evolvishub_data_handler/cli.py
evolvishub_data_handler/config.py
evolvishub_data_handler/config_loader.py
evolvishub_data_handler/multi_cdc_handler.py
evolvishub_data_handler/watermark_manager.py
evolvishub_data_handler/adapters/base.py
evolvishub_data_handler/adapters/factory.py
evolvishub_data_handler/adapters/file.py
evolvishub_data_handler/adapters/kafka.py
evolvishub_data_handler/adapters/mongodb.py
evolvishub_data_handler/adapters/mysql.py
evolvishub_data_handler/adapters/oracle.py
evolvishub_data_handler/adapters/postgresql.py
evolvishub_data_handler/adapters/pulsar.py
evolvishub_data_handler/adapters/rabbitmq.py
evolvishub_data_handler/adapters/redis_streams.py
evolvishub_data_handler/adapters/s3.py
evolvishub_data_handler/adapters/sqlite.py
evolvishub_data_handler/adapters/sqlserver.py
evolvishub_data_handler/plugins/__init__.py
evolvishub_data_handler/plugins/adapters.py
evolvishub_data_handler/plugins/base.py
evolvishub_data_handler/plugins/hooks.py
evolvishub_data_handler/plugins/manager.py
evolvishub_data_handler/plugins/middleware.py
evolvishub_data_handler/plugins/transformers.py
evolvishub_data_handler-2.2.0.dist-info/licenses/LICENSE
tests/__init__.py
tests/conftest.py
tests/test_cdc_handler.py
tests/test_cli.py
tests/test_config.py
tests/test_event_bus_adapters.py
tests/test_kafka_adapter.py
tests/test_middleware.py
tests/test_multi_cdc.py
tests/test_optional_plugins.py
tests/test_oracle_adapter.py
tests/test_postgresql_adapter.py
tests/test_sqlite_adapter.py
tests/test_sync_modes.py
tests/test_transformers.py
tests/test_watermark_storage.py
evolvishub_data_handler-2.2.0.dist-info/METADATA
evolvishub_data_handler-2.2.0.dist-info/WHEEL
evolvishub_data_handler-2.2.0.dist-info/entry_points.txt
evolvishub_data_handler-2.2.0.dist-info/top_level.txt
evolvishub_data_handler-2.2.0.dist-info/RECORD
