Metadata-Version: 2.4
Name: evolvishub-data-handler
Version: 2.2.0
Summary: A Change Data Capture (CDC) library for data synchronization
Home-page: https://github.com/evolvishub/evolvishub-data-handler
Author: Alban Maxhuni, PhD
Author-email: EvolvisHub <info@evolvishub.com>
License: Commercial License with Open Source Exception
Classifier: Development Status :: 4 - Beta
Classifier: Intended Audience :: Developers
Classifier: License :: Other/Proprietary License
Classifier: Operating System :: OS Independent
Classifier: Programming Language :: Python :: 3
Classifier: Programming Language :: Python :: 3.8
Classifier: Programming Language :: Python :: 3.9
Classifier: Programming Language :: Python :: 3.10
Classifier: Programming Language :: Python :: 3.11
Classifier: Topic :: Database
Classifier: Topic :: Software Development :: Libraries :: Python Modules
Requires-Python: >=3.8
License-File: LICENSE
Requires-Dist: sqlalchemy>=2.0.0
Requires-Dist: psycopg2-binary>=2.9.0
Requires-Dist: mysql-connector-python>=8.0.0
Requires-Dist: pymssql>=2.2.0
Requires-Dist: oracledb>=1.0.0
Requires-Dist: pymongo>=4.0.0
Requires-Dist: boto3>=1.26.0
Requires-Dist: google-cloud-storage>=2.0.0
Requires-Dist: azure-storage-blob>=12.0.0
Requires-Dist: pandas>=2.0.0
Requires-Dist: pyarrow>=12.0.0
Requires-Dist: pydantic>=2.0.0
Requires-Dist: pyyaml>=6.0.0
Requires-Dist: python-dotenv>=1.0.0
Requires-Dist: loguru>=0.7.0
Requires-Dist: croniter>=1.3.0
Requires-Dist: click>=8.0.0
Requires-Dist: pytz>=2023.3
Provides-Extra: dev
Requires-Dist: pytest>=7.0.0; extra == "dev"
Requires-Dist: pytest-cov>=4.0.0; extra == "dev"
Requires-Dist: black>=23.0.0; extra == "dev"
Requires-Dist: isort>=5.0.0; extra == "dev"
Requires-Dist: mypy>=1.0.0; extra == "dev"
Requires-Dist: flake8>=6.0.0; extra == "dev"
Requires-Dist: pre-commit>=3.0.0; extra == "dev"
Requires-Dist: flake8-docstrings>=1.7.0; extra == "dev"
Requires-Dist: flake8-bugbear>=23.0.0; extra == "dev"
Requires-Dist: flake8-comprehensions>=3.12.0; extra == "dev"
Requires-Dist: flake8-simplify>=0.20.0; extra == "dev"
Requires-Dist: types-all>=1.0.0; extra == "dev"
Requires-Dist: types-pydantic>=2.0.0; extra == "dev"
Requires-Dist: types-sqlalchemy>=2.0.0; extra == "dev"
Requires-Dist: types-boto3>=1.0.0; extra == "dev"
Requires-Dist: types-pymongo>=4.0.0; extra == "dev"
Requires-Dist: types-pandas>=2.0.0; extra == "dev"
Provides-Extra: docs
Requires-Dist: sphinx>=7.0.0; extra == "docs"
Requires-Dist: sphinx-rtd-theme>=1.0.0; extra == "docs"
Requires-Dist: sphinx-autodoc-typehints>=1.0.0; extra == "docs"
Dynamic: author
Dynamic: home-page
Dynamic: license-file
Dynamic: requires-python
